oggmap/__init__.py
oggmap/__main__.py
oggmap/cds2aa.py
oggmap/datasets.py
oggmap/eggnog2orthomap.py
oggmap/gtf2t2g.py
oggmap/ncbitax.py
oggmap/of2orthomap.py
oggmap/orthomap2tei.py
oggmap/orthomcl2orthomap.py
oggmap/plaza2orthomap.py
oggmap/qlin.py
oggmap-0.0.1.dist-info/LICENSE
oggmap-0.0.1.dist-info/METADATA
oggmap-0.0.1.dist-info/WHEEL
oggmap-0.0.1.dist-info/entry_points.txt
oggmap-0.0.1.dist-info/top_level.txt
oggmap-0.0.1.dist-info/RECORD
